basd/__init__.py
basd/__main__.py
basd/requirements.py
basd/_static/basd-logo.png
basd/_static/fraunhofer-iisb-logo.png
basd/cad/__init__.py
basd/cad/cad_base.py
basd/cad/cad_battery_module.py
basd/cad/cad_battery_pack.py
basd/cad/cad_battery_string.py
basd/cad/cad_cell.py
basd/cad/cad_cell_block.py
basd/cad/cad_system_definition.py
basd/cad/cell_dimensions/standard_cylindrical.stp
basd/cad/cell_dimensions/standard_pouch.stp
basd/cad/cell_dimensions/standard_prismatic.stp
basd/database/__init__.py
basd/database/battery_cell.py
basd/database/cell_data/__init__.py
basd/database/cell_data/descriptors.py
basd/database/db_schema/basics.schema.json
basd/database/db_schema/db.schema.json
basd/database/db_schema/identification.schema.json
basd/designer/__init__.py
basd/designer/basic_sets.py
basd/designer/cooling.py
basd/designer/find_parameter_sets.py
basd/designer/overhead_functions.py
basd/designer/overhead_functions_abc.py
basd/designer/parameter_set.py
basd/designer/system_design.py
basd/simulation/__init__.py
basd/simulation/container.py
basd/simulation/model_api.py
basd/simulation/visualization_api.py
basd/simulation/model/__init__.py
basd/simulation/model/soc/__init__.py
basd/simulation/model/soh/__init__.py
basd/simulation/model/thermal/__init__.py
basd/simulation/plot/__init__.py
basd/utils/__init__.py
basd/utils/basd_version.py
basd/utils/logo.py
basd-2024.3.0.dist-info/entry_points.txt
basd-2024.3.0.dist-info/LICENSE
basd-2024.3.0.dist-info/WHEEL
basd-2024.3.0.dist-info/METADATA
basd-2024.3.0.dist-info/RECORD
