Metadata-Version: 2.1
Name: basd
Version: 2024.3.0
Summary: Implements the command line interface to the Battery System Designer tool.
Author-email: The foxBMS Team <info@foxbms.org>
Requires-Python: >=3.10,<3.12
Classifier: Development Status :: 2 - Pre-Alpha
Classifier: Environment :: Console
Classifier: Intended Audience :: Developers
Classifier: Natural Language :: English
Classifier: Programming Language :: Python :: 3
Classifier: Programming Language :: Python :: 3.10
Classifier: Topic :: Scientific/Engineering
Classifier: Topic :: Scientific/Engineering :: Artificial Intelligence
Classifier: Topic :: Scientific/Engineering :: Physics
Classifier: Topic :: Scientific/Engineering :: Visualization
Requires-Dist: cadquery>=2.2.0
Requires-Dist: click>=8.1.3
Requires-Dist: colorama>=0.4.6
Requires-Dist: joblib>=1.2.0
Requires-Dist: jsonschema>=4.17.3
Requires-Dist: matplotlib>=3.7.1
Requires-Dist: numpy>=1.24.2
Requires-Dist: pandas>=2.0.0
Requires-Dist: platformdirs>=3.5.0
Requires-Dist: scipy>=1.10.1
Requires-Dist: black==23.3.0 ; extra == "dev"
Requires-Dist: isort==5.12.0 ; extra == "dev"
Requires-Dist: pylint==2.17.3 ; extra == "dev"
Requires-Dist: mypy==1.2.0 ; extra == "dev"
Requires-Dist: sphinx ; extra == "doc"
Requires-Dist: sphinxcontrib-programoutput ; extra == "doc"
Requires-Dist: furo ; extra == "doc"
Requires-Dist: sphinxcontrib-spelling ; extra == "doc"
Requires-Dist: pytest >=2.7.3 ; extra == "test"
Requires-Dist: pytest-cov ; extra == "test"
Project-URL: Documentation, https://basd.readthedocs.io
Project-URL: Home, https://github.com/foxBMS/basd
Project-URL: Source, https://github.com/foxBMS/basd
Provides-Extra: dev
Provides-Extra: doc
Provides-Extra: test
